causaliq_analysis/__init__.py
causaliq_analysis/cli.py
causaliq_analysis/graph.py
causaliq_analysis/metrics.py
causaliq_analysis/trace.py
causaliq_analysis-0.2.0.dist-info/licenses/LICENSE
causaliq_analysis-0.2.0.dist-info/METADATA
causaliq_analysis-0.2.0.dist-info/WHEEL
causaliq_analysis-0.2.0.dist-info/entry_points.txt
causaliq_analysis-0.2.0.dist-info/top_level.txt
causaliq_analysis-0.2.0.dist-info/RECORD
